{"url":"http://allpurposeloans.co.uk/","isFake":false,"links":["https://live-allpurposeloans-cdn.azureedge.net/","https://live-allpurposeloans-cdn.azureedge.net/images/favicon.png","https://live-allpurposeloans-cdn.azureedge.net/js/APL.common.min.js?v=izxS-BjXr_fSEGMaeDxJNirkfxH4neVdx6uN18VyPnw","https://www.googletagmanager.com/gtm.js?id=GTM-WM3WCPB","https://live-allpurposeloans-cdn.azureedge.net/images/EF-Logo-light-bg.svg","https://live-allpurposeloans-cdn.azureedge.net/images/believe_money_logo.svg","https://live-allpurposeloans-cdn.azureedge.net/versions/10.8.1/images/hero.webp","https://live-allpurposeloans-cdn.azureedge.net/versions/10.8.1/images/hero-bg-mobile.webp","https://live-allpurposeloans-cdn.azureedge.net/versions/10.8.1/images/apl_mbl_loan.webp","https://live-allpurposeloans-cdn.azureedge.net/versions/10.8.1/images/quotes-bg.webp","https://live-allpurposeloans-cdn.azureedge.net/images/lenders/zopa.png","https://live-allpurposeloans-cdn.azureedge.net/images/lenders/tandem.png","https://live-allpurposeloans-cdn.azureedge.net/images/lenders/admiral.png","https://live-allpurposeloans-cdn.azureedge.net/images/lenders/bamboo.png","https://live-allpurposeloans-cdn.azureedge.net/images/lenders/lendable.png","https://live-allpurposeloans-cdn.azureedge.net/images/lenders/shawbrook.png","https://live-allpurposeloans-cdn.azureedge.net/images/lenders/creditplus.png","https://live-allpurposeloans-cdn.azureedge.net/images/lenders/jnbank.png","https://live-allpurposeloans-cdn.azureedge.net/images/lenders/everydayloans.png","https://live-allpurposeloans-cdn.azureedge.net/images/lenders/118118money.png","https://register.fca.org.uk/ShPo_firmdetailsPage?id=0010X00004D8GbnQAF","https://www.allpurposeloans.co.uk/cookiesnotice","https://cdn-ukwest.onetrust.com/logos/0eb7aab4-e9d0-4d2d-8aff-5fd8c3dfcd97/42450972-7bc4-49db-8e6f-adbc6151d8fd/593d760c-572b-4f7f-aee7-09b5b283dbe8/logo.png","https://www.cookiepro.com/products/cookie-consent/","https://cdn-ukwest.onetrust.com/logos/static/poweredBy_cp_logo.svg"],"prices":[{"price":4000,"code":"GBP","discount":0,"hasPercentage":false,"hasLineThrough":false},{"price":5382.96,"code":"GBP","discount":0,"hasPercentage":false,"hasLineThrough":false},{"price":224.29,"code":"GBP","discount":0,"hasPercentage":false,"hasLineThrough":false},{"price":75000,"code":"GBP","discount":0,"hasPercentage":false,"hasLineThrough":false},{"price":758.12,"code":"GBP","discount":0,"hasPercentage":false,"hasLineThrough":false},{"price":79295,"code":"GBP","discount":0,"hasPercentage":false,"hasLineThrough":false},{"price":136461.6,"code":"GBP","discount":0,"hasPercentage":false,"hasLineThrough":false},{"price":1295,"code":"GBP","discount":0,"hasPercentage":false,"hasLineThrough":false},{"price":3000,"code":"GBP","discount":0,"hasPercentage":false,"hasLineThrough":false}]}