{"url":"http://flashlightz.com/","isFake":false,"links":["https://flashlightz.com/","https://shopify-fast-tags.deliverr.com/main.js?shop=flashlightz-2023.myshopify.com","https://shop.app/","https://shop.app/checkouts/internal/preloads.js?locale=en-US&shop_id=70213271850","https://tools.luckyorange.com/core/lo.js?site-id=36d88bd6","https://config.gorgias.chat/bundle-loader/shopify/flashlightz-2023.myshopify.com","https://bundle.dyn-rev.app/loader.js?shop_name=flashlightz-2023","https://config.gorgias.help/api/contact-forms/replace-mailto-script.js?shopName=flashlightz-2023","https://cdn.shopify.com/extensions/8c7e1969-cbb1-4ff8-8b6c-43966f9d53a9/1.41.0/assets/main.js","https://monorail-edge.shopifysvc.com/","https://flashlightz.com/cdn/wpm/bd996b560w734f31f6pceb6670bm452f95e0m.js","https://flashlightz.com/cdn/shopifycloud/perf-kit/shopify-perf-kit-1.4.0.min.js","https://assets.gorgias.chat/build/static/js/focustrap.f8e0a326622a702c.js","https://assets.gorgias.chat/build/static/js/846.0e9f6b00c63463cf.js","https://assets.gorgias.chat/build/static/js/gcmw.59f00fa0745a401c.js","https://cdn.shopify.com/shopifycloud/checkout-web/assets/","https://cdn.shopify.com/shopifycloud/checkout-web/assets/c1.en/polyfills.I3JIKAFZ.js","https://cdn.shopify.com/shopifycloud/checkout-web/assets/c1.en/app.D5l4c8gz.js","https://cdn.shopify.com/shopifycloud/checkout-web/assets/c1.en/page-OnePage.nQdpykK8.js","https://cdn.shopify.com/shopifycloud/checkout-web/assets/c1.en/DeliveryMethodSelectorSection.CWRc9obX.js","https://cdn.shopify.com/shopifycloud/checkout-web/assets/c1.en/useEditorShopPayNavigation.BSwrSykE.js","https://cdn.shopify.com/shopifycloud/checkout-web/assets/c1.en/VaultedPayment.DIE-UHvT.js","https://cdn.shopify.com/shopifycloud/checkout-web/assets/c1.en/LocalizationExtensionField.LA8rqilW.js","https://cdn.shopify.com/shopifycloud/checkout-web/assets/c1.en/ShopPayOptInDisclaimer.C299Y72f.js","https://cdn.shopify.com/shopifycloud/checkout-web/assets/c1.en/RememberMeDescriptionText.D73KH0Fg.js","https://cdn.shopify.com/shopifycloud/checkout-web/assets/c1.en/UnavailableInBuyerLocationBanner.Do8i_-C7.js","https://cdn.shopify.com/shopifycloud/checkout-web/assets/c1.en/PayButtonSection.TvUpRVMK.js","https://cdn.shopify.com/shopifycloud/checkout-web/assets/c1.en/component-ShopPayVerificationSwitch.DRZmddkO.js","https://cdn.shopify.com/shopifycloud/checkout-web/assets/c1.en/useSubscribeMessenger.CouxfX_u.js","https://cdn.shopify.com/shopifycloud/checkout-web/assets/c1.en/index.DzuhxRKA.js","https://twitter.com/flashlightzguy","https://www.facebook.com/FlashlightZ-799833973436202/timeline","https://www.instagram.com/flashlightzteam/","https://www.youtube.com/channel/UCGOghB1yjm5PkvLJqhWfzwQ","https://flashlightz-2023.myshopify.com/account/login","https://www.shopify.com/?utm_campaign=poweredby&utm_medium=shopify&utm_source=onlinestore","https://flashlightz.com/wpm@d996b560w734f31f6pceb6670bm452f95e0/custom/web-pixel-shopify-custom-pixel@0290/sandbox/modern/","https://config.gorgias.chat/gorgias-chat-bundle.js?rev=a8949718&appKey=01J4MR1Q727F2JW3WEFA48R628","https://bundle.dyn-rev.app/script.js?rev=ddf6f91","https://flashlightz-2023.shopify-checkout.config.gorgias.chat/shopify-checkout-chat-storage-sync"],"prices":[{"price":79.95,"code":"USD","discount":0,"hasPercentage":false,"hasLineThrough":false},{"price":64.95,"code":"USD","discount":0,"hasPercentage":false,"hasLineThrough":false},{"price":89.95,"code":"USD","discount":0,"hasPercentage":false,"hasLineThrough":false},{"price":139.95,"code":"USD","discount":0,"hasPercentage":false,"hasLineThrough":false},{"price":139.95,"code":"USD","discount":0,"hasPercentage":false,"hasLineThrough":false},{"price":129.95,"code":"USD","discount":0,"hasPercentage":false,"hasLineThrough":false},{"price":139.95,"code":"USD","discount":0,"hasPercentage":false,"hasLineThrough":true},{"price":124.95,"code":"USD","discount":0,"hasPercentage":false,"hasLineThrough":false},{"price":99.95,"code":"USD","discount":0,"hasPercentage":false,"hasLineThrough":false},{"price":36.95,"code":"USD","discount":0,"hasPercentage":false,"hasLineThrough":false},{"price":119.95,"code":"USD","discount":0,"hasPercentage":false,"hasLineThrough":false},{"price":119.95,"code":"USD","discount":0,"hasPercentage":false,"hasLineThrough":false},{"price":29.95,"code":"USD","discount":0,"hasPercentage":false,"hasLineThrough":false},{"price":36.95,"code":"USD","discount":0,"hasPercentage":false,"hasLineThrough":false},{"price":99.95,"code":"USD","discount":0,"hasPercentage":false,"hasLineThrough":false},{"price":119.95,"code":"USD","discount":0,"hasPercentage":false,"hasLineThrough":false},{"price":99.95,"code":"USD","discount":0,"hasPercentage":false,"hasLineThrough":false},{"price":129.95,"code":"USD","discount":0,"hasPercentage":false,"hasLineThrough":false},{"price":79.95,"code":"USD","discount":0,"hasPercentage":false,"hasLineThrough":false}]}