{"url":"http://kicksown.com/","isFake":false,"links":[],"prices":[{"price":159,"code":"USD","discount":0,"hasPercentage":false,"hasLineThrough":false},{"price":159,"code":"USD","discount":0,"hasPercentage":false,"hasLineThrough":false},{"price":119,"code":"USD","discount":0,"hasPercentage":false,"hasLineThrough":false},{"price":145,"code":"USD","discount":0,"hasPercentage":false,"hasLineThrough":false},{"price":275,"code":"USD","discount":0,"hasPercentage":false,"hasLineThrough":false},{"price":179,"code":"USD","discount":0,"hasPercentage":false,"hasLineThrough":false},{"price":149,"code":"USD","discount":0,"hasPercentage":false,"hasLineThrough":false},{"price":89,"code":"USD","discount":0,"hasPercentage":false,"hasLineThrough":false},{"price":95,"code":"USD","discount":0,"hasPercentage":false,"hasLineThrough":false},{"price":99,"code":"USD","discount":0,"hasPercentage":false,"hasLineThrough":false}]}