{"url":"http://kissbo.com/","isFake":false,"links":[],"prices":[{"price":199.95,"code":"USD","discount":0,"hasPercentage":false,"hasLineThrough":false},{"price":59,"code":"USD","discount":0,"hasPercentage":false,"hasLineThrough":true},{"price":119.95,"code":"USD","discount":0,"hasPercentage":false,"hasLineThrough":false},{"price":269.95,"code":"USD","discount":0,"hasPercentage":false,"hasLineThrough":true},{"price":219.95,"code":"USD","discount":0,"hasPercentage":false,"hasLineThrough":false},{"price":89.95,"code":"USD","discount":0,"hasPercentage":false,"hasLineThrough":false},{"price":109.99,"code":"USD","discount":0,"hasPercentage":false,"hasLineThrough":true},{"price":105.95,"code":"USD","discount":0,"hasPercentage":false,"hasLineThrough":false},{"price":26.95,"code":"USD","discount":0,"hasPercentage":false,"hasLineThrough":true},{"price":19.95,"code":"USD","discount":0,"hasPercentage":false,"hasLineThrough":false},{"price":95.95,"code":"USD","discount":0,"hasPercentage":false,"hasLineThrough":false},{"price":25.95,"code":"USD","discount":0,"hasPercentage":false,"hasLineThrough":true},{"price":19.95,"code":"USD","discount":0,"hasPercentage":false,"hasLineThrough":false},{"price":19.95,"code":"USD","discount":0,"hasPercentage":false,"hasLineThrough":false},{"price":55.95,"code":"USD","discount":0,"hasPercentage":false,"hasLineThrough":true},{"price":49.95,"code":"USD","discount":0,"hasPercentage":false,"hasLineThrough":false},{"price":45,"code":"USD","discount":0,"hasPercentage":false,"hasLineThrough":true},{"price":33.95,"code":"USD","discount":0,"hasPercentage":false,"hasLineThrough":false},{"price":9.95,"code":"USD","discount":0,"hasPercentage":false,"hasLineThrough":false},{"price":15.95,"code":"USD","discount":0,"hasPercentage":false,"hasLineThrough":false},{"price":12.95,"code":"USD","discount":0,"hasPercentage":false,"hasLineThrough":false},{"price":11.95,"code":"USD","discount":0,"hasPercentage":false,"hasLineThrough":false},{"price":119.95,"code":"USD","discount":0,"hasPercentage":false,"hasLineThrough":false},{"price":59,"code":"USD","discount":0,"hasPercentage":false,"hasLineThrough":true},{"price":149.95,"code":"USD","discount":0,"hasPercentage":false,"hasLineThrough":false}]}