{"url":"http://testequipmentusa.com/","isFake":false,"links":[],"prices":[{"price":0,"code":"USD","discount":0,"hasPercentage":false,"hasLineThrough":false},{"price":0.92,"code":"USD","discount":0,"hasPercentage":false,"hasLineThrough":false},{"price":6.5,"code":"USD","discount":0,"hasPercentage":false,"hasLineThrough":false},{"price":2.5,"code":"USD","discount":0,"hasPercentage":false,"hasLineThrough":false},{"price":13.78,"code":"USD","discount":0,"hasPercentage":false,"hasLineThrough":false},{"price":7.13,"code":"USD","discount":0,"hasPercentage":false,"hasLineThrough":false},{"price":3.61,"code":"USD","discount":0,"hasPercentage":false,"hasLineThrough":false},{"price":7.6,"code":"USD","discount":0,"hasPercentage":false,"hasLineThrough":false},{"price":7.55,"code":"USD","discount":0,"hasPercentage":false,"hasLineThrough":false},{"price":15.2,"code":"USD","discount":0,"hasPercentage":false,"hasLineThrough":false},{"price":259.63,"code":"USD","discount":0,"hasPercentage":false,"hasLineThrough":false},{"price":12.24,"code":"USD","discount":0,"hasPercentage":false,"hasLineThrough":false},{"price":21.85,"code":"USD","discount":0,"hasPercentage":false,"hasLineThrough":false},{"price":12225,"code":"USD","discount":0,"hasPercentage":false,"hasLineThrough":false},{"price":9265,"code":"USD","discount":0,"hasPercentage":false,"hasLineThrough":false},{"price":19805,"code":"USD","discount":0,"hasPercentage":false,"hasLineThrough":false},{"price":3570,"code":"USD","discount":0,"hasPercentage":false,"hasLineThrough":false},{"price":3740,"code":"USD","discount":0,"hasPercentage":false,"hasLineThrough":false},{"price":14405,"code":"USD","discount":0,"hasPercentage":false,"hasLineThrough":false},{"price":288,"code":"USD","discount":0,"hasPercentage":false,"hasLineThrough":false},{"price":0,"code":"USD","discount":0,"hasPercentage":false,"hasLineThrough":false},{"price":365,"code":"USD","discount":0,"hasPercentage":false,"hasLineThrough":false},{"price":2290,"code":"USD","discount":0,"hasPercentage":false,"hasLineThrough":false},{"price":2190,"code":"USD","discount":0,"hasPercentage":false,"hasLineThrough":false},{"price":1950,"code":"USD","discount":0,"hasPercentage":false,"hasLineThrough":false},{"price":250,"code":"USD","discount":0,"hasPercentage":false,"hasLineThrough":false},{"price":293.84,"code":"USD","discount":0,"hasPercentage":false,"hasLineThrough":false},{"price":410,"code":"USD","discount":0,"hasPercentage":false,"hasLineThrough":false},{"price":460.8,"code":"USD","discount":0,"hasPercentage":false,"hasLineThrough":false},{"price":229,"code":"USD","discount":0,"hasPercentage":false,"hasLineThrough":false},{"price":230,"code":"USD","discount":0,"hasPercentage":false,"hasLineThrough":false},{"price":569.05,"code":"USD","discount":0,"hasPercentage":false,"hasLineThrough":false},{"price":172.87,"code":"USD","discount":0,"hasPercentage":false,"hasLineThrough":false},{"price":567.15,"code":"USD","discount":0,"hasPercentage":false,"hasLineThrough":false},{"price":159.75,"code":"USD","discount":0,"hasPercentage":false,"hasLineThrough":false},{"price":1197.9,"code":"USD","discount":0,"hasPercentage":false,"hasLineThrough":false},{"price":1431,"code":"USD","discount":0,"hasPercentage":false,"hasLineThrough":false},{"price":1565,"code":"USD","discount":0,"hasPercentage":false,"hasLineThrough":false}]}