{"url":"http://tickledpet.com/","isFake":false,"links":[],"prices":[{"price":13.99,"code":"USD","discount":0,"hasPercentage":false,"hasLineThrough":false},{"price":16.97,"code":"USD","discount":0,"hasPercentage":false,"hasLineThrough":false},{"price":32.99,"code":"USD","discount":0,"hasPercentage":false,"hasLineThrough":false},{"price":10.97,"code":"USD","discount":0,"hasPercentage":false,"hasLineThrough":false},{"price":24.99,"code":"USD","discount":0.24,"hasPercentage":false,"hasLineThrough":false},{"price":8.99,"code":"USD","discount":0,"hasPercentage":false,"hasLineThrough":false}]}