{"url":"http://bettenfist.com/","isFake":true,"links":[],"prices":[{"price":219,"code":"EUR","discount":0,"hasPercentage":false,"hasLineThrough":true},{"price":95.99,"code":"EUR","discount":0,"hasPercentage":false,"hasLineThrough":false},{"price":424,"code":"EUR","discount":0,"hasPercentage":false,"hasLineThrough":true},{"price":96.99,"code":"EUR","discount":0,"hasPercentage":false,"hasLineThrough":false},{"price":469,"code":"EUR","discount":0,"hasPercentage":false,"hasLineThrough":true},{"price":94.99,"code":"EUR","discount":0,"hasPercentage":false,"hasLineThrough":false},{"price":579,"code":"EUR","discount":0,"hasPercentage":false,"hasLineThrough":true},{"price":96.99,"code":"EUR","discount":0,"hasPercentage":false,"hasLineThrough":false},{"price":437,"code":"EUR","discount":0,"hasPercentage":false,"hasLineThrough":true},{"price":97.99,"code":"EUR","discount":0,"hasPercentage":false,"hasLineThrough":false},{"price":413,"code":"EUR","discount":0,"hasPercentage":false,"hasLineThrough":true},{"price":96.99,"code":"EUR","discount":0,"hasPercentage":false,"hasLineThrough":false},{"price":417,"code":"EUR","discount":0,"hasPercentage":false,"hasLineThrough":true},{"price":98.99,"code":"EUR","discount":0,"hasPercentage":false,"hasLineThrough":false},{"price":480,"code":"EUR","discount":0,"hasPercentage":false,"hasLineThrough":true},{"price":95.99,"code":"EUR","discount":0,"hasPercentage":false,"hasLineThrough":false},{"price":458,"code":"EUR","discount":0,"hasPercentage":false,"hasLineThrough":true},{"price":94.99,"code":"EUR","discount":0,"hasPercentage":false,"hasLineThrough":false},{"price":539,"code":"EUR","discount":0,"hasPercentage":false,"hasLineThrough":true},{"price":99.99,"code":"EUR","discount":0,"hasPercentage":false,"hasLineThrough":false},{"price":472,"code":"EUR","discount":0,"hasPercentage":false,"hasLineThrough":true},{"price":98.99,"code":"EUR","discount":0,"hasPercentage":false,"hasLineThrough":false},{"price":540,"code":"EUR","discount":0,"hasPercentage":false,"hasLineThrough":true},{"price":94.99,"code":"EUR","discount":0,"hasPercentage":false,"hasLineThrough":false},{"price":539,"code":"EUR","discount":0,"hasPercentage":false,"hasLineThrough":true},{"price":99.99,"code":"EUR","discount":0,"hasPercentage":false,"hasLineThrough":false},{"price":411,"code":"EUR","discount":0,"hasPercentage":false,"hasLineThrough":true},{"price":99.99,"code":"EUR","discount":0,"hasPercentage":false,"hasLineThrough":false},{"price":499,"code":"EUR","discount":0,"hasPercentage":false,"hasLineThrough":true},{"price":94.99,"code":"EUR","discount":0,"hasPercentage":false,"hasLineThrough":false},{"price":548,"code":"EUR","discount":0,"hasPercentage":false,"hasLineThrough":true},{"price":95.99,"code":"EUR","discount":0,"hasPercentage":false,"hasLineThrough":false},{"price":149,"code":"EUR","discount":0,"hasPercentage":false,"hasLineThrough":true},{"price":98.99,"code":"EUR","discount":0,"hasPercentage":false,"hasLineThrough":false},{"price":229,"code":"EUR","discount":0,"hasPercentage":false,"hasLineThrough":true},{"price":97.99,"code":"EUR","discount":0,"hasPercentage":false,"hasLineThrough":false},{"price":199,"code":"EUR","discount":0,"hasPercentage":false,"hasLineThrough":true},{"price":95.99,"code":"EUR","discount":0,"hasPercentage":false,"hasLineThrough":false},{"price":571,"code":"EUR","discount":0,"hasPercentage":false,"hasLineThrough":true},{"price":99.99,"code":"EUR","discount":0,"hasPercentage":false,"hasLineThrough":false},{"price":413,"code":"EUR","discount":0,"hasPercentage":false,"hasLineThrough":true},{"price":96.99,"code":"EUR","discount":0,"hasPercentage":false,"hasLineThrough":false},{"price":502,"code":"EUR","discount":0,"hasPercentage":false,"hasLineThrough":true},{"price":98.99,"code":"EUR","discount":0,"hasPercentage":false,"hasLineThrough":false},{"price":590,"code":"EUR","discount":0,"hasPercentage":false,"hasLineThrough":true},{"price":96.99,"code":"EUR","discount":0,"hasPercentage":false,"hasLineThrough":false},{"price":403,"code":"EUR","discount":0,"hasPercentage":false,"hasLineThrough":true},{"price":97.99,"code":"EUR","discount":0,"hasPercentage":false,"hasLineThrough":false},{"price":568,"code":"EUR","discount":0,"hasPercentage":false,"hasLineThrough":true},{"price":97.99,"code":"EUR","discount":0,"hasPercentage":false,"hasLineThrough":false},{"price":491,"code":"EUR","discount":0,"hasPercentage":false,"hasLineThrough":true},{"price":97.99,"code":"EUR","discount":0,"hasPercentage":false,"hasLineThrough":false},{"price":407,"code":"EUR","discount":0,"hasPercentage":false,"hasLineThrough":true},{"price":99.99,"code":"EUR","discount":0,"hasPercentage":false,"hasLineThrough":false},{"price":403,"code":"EUR","discount":0,"hasPercentage":false,"hasLineThrough":true},{"price":99.99,"code":"EUR","discount":0,"hasPercentage":false,"hasLineThrough":false}]}