{"url":"http://merlin-apotheke.com/","isFake":true,"links":["https://www.merlin-apotheke.com/","https://www.merlin-apotheke.com/potenzmittel","https://www.merlin-apotheke.com/cialis-kaufen","https://www.merlin-apotheke.com/viagra-kaufen"],"prices":[{"price":37,"code":"EUR","discount":0,"hasPercentage":false,"hasLineThrough":false},{"price":20,"code":"EUR","discount":0,"hasPercentage":false,"hasLineThrough":false},{"price":28.17,"code":"EUR","discount":0,"hasPercentage":false,"hasLineThrough":false},{"price":29,"code":"EUR","discount":0,"hasPercentage":false,"hasLineThrough":false},{"price":18,"code":"EUR","discount":0,"hasPercentage":false,"hasLineThrough":false},{"price":30,"code":"EUR","discount":0,"hasPercentage":false,"hasLineThrough":false},{"price":28,"code":"EUR","discount":0,"hasPercentage":false,"hasLineThrough":false},{"price":32,"code":"EUR","discount":0,"hasPercentage":false,"hasLineThrough":false},{"price":34,"code":"EUR","discount":0,"hasPercentage":false,"hasLineThrough":false},{"price":35,"code":"EUR","discount":0,"hasPercentage":false,"hasLineThrough":false},{"price":38,"code":"EUR","discount":0,"hasPercentage":false,"hasLineThrough":false},{"price":28,"code":"EUR","discount":0,"hasPercentage":false,"hasLineThrough":false},{"price":38,"code":"EUR","discount":0,"hasPercentage":false,"hasLineThrough":false},{"price":19,"code":"EUR","discount":0,"hasPercentage":false,"hasLineThrough":false},{"price":16,"code":"EUR","discount":0,"hasPercentage":false,"hasLineThrough":false},{"price":37,"code":"EUR","discount":0,"hasPercentage":false,"hasLineThrough":false},{"price":20,"code":"EUR","discount":0,"hasPercentage":false,"hasLineThrough":false},{"price":28.17,"code":"EUR","discount":0,"hasPercentage":false,"hasLineThrough":false},{"price":29,"code":"EUR","discount":0,"hasPercentage":false,"hasLineThrough":false},{"price":18,"code":"EUR","discount":0,"hasPercentage":false,"hasLineThrough":false},{"price":30,"code":"EUR","discount":0,"hasPercentage":false,"hasLineThrough":false},{"price":28,"code":"EUR","discount":0,"hasPercentage":false,"hasLineThrough":false},{"price":32,"code":"EUR","discount":0,"hasPercentage":false,"hasLineThrough":false},{"price":34,"code":"EUR","discount":0,"hasPercentage":false,"hasLineThrough":false},{"price":35,"code":"EUR","discount":0,"hasPercentage":false,"hasLineThrough":false},{"price":38,"code":"EUR","discount":0,"hasPercentage":false,"hasLineThrough":false},{"price":28,"code":"EUR","discount":0,"hasPercentage":false,"hasLineThrough":false},{"price":38,"code":"EUR","discount":0,"hasPercentage":false,"hasLineThrough":false},{"price":19,"code":"EUR","discount":0,"hasPercentage":false,"hasLineThrough":false},{"price":16,"code":"EUR","discount":0,"hasPercentage":false,"hasLineThrough":false}]}