{"url":"http://misterlamp.de/","isFake":true,"links":[],"prices":[{"price":44.95,"code":"EUR","discount":0.55,"hasPercentage":false,"hasLineThrough":false},{"price":39.95,"code":"EUR","discount":0.5,"hasPercentage":false,"hasLineThrough":false},{"price":59.95,"code":"EUR","discount":0.5,"hasPercentage":false,"hasLineThrough":false},{"price":54.95,"code":"EUR","discount":0.54,"hasPercentage":false,"hasLineThrough":false},{"price":79.95,"code":"EUR","discount":0.67,"hasPercentage":false,"hasLineThrough":false},{"price":59.95,"code":"EUR","discount":0.5,"hasPercentage":false,"hasLineThrough":false},{"price":79.95,"code":"EUR","discount":0.67,"hasPercentage":false,"hasLineThrough":false},{"price":59.95,"code":"EUR","discount":0.54,"hasPercentage":false,"hasLineThrough":false},{"price":94.95,"code":"EUR","discount":0.5,"hasPercentage":false,"hasLineThrough":false},{"price":59.95,"code":"EUR","discount":0.4,"hasPercentage":false,"hasLineThrough":false},{"price":54.95,"code":"EUR","discount":0.5,"hasPercentage":false,"hasLineThrough":false},{"price":124.95,"code":"EUR","discount":0.5,"hasPercentage":false,"hasLineThrough":false}]}