{"url":"http://monsroyales.com/","isFake":true,"links":[],"prices":[{"price":230,"code":"USD","discount":0,"hasPercentage":false,"hasLineThrough":true},{"price":88.99,"code":"USD","discount":0,"hasPercentage":false,"hasLineThrough":false},{"price":350,"code":"USD","discount":0,"hasPercentage":false,"hasLineThrough":true},{"price":96.99,"code":"USD","discount":0,"hasPercentage":false,"hasLineThrough":false},{"price":230,"code":"USD","discount":0,"hasPercentage":false,"hasLineThrough":true},{"price":90.99,"code":"USD","discount":0,"hasPercentage":false,"hasLineThrough":false},{"price":170,"code":"USD","discount":0,"hasPercentage":false,"hasLineThrough":true},{"price":91.99,"code":"USD","discount":0,"hasPercentage":false,"hasLineThrough":false},{"price":350,"code":"USD","discount":0,"hasPercentage":false,"hasLineThrough":true},{"price":93.99,"code":"USD","discount":0,"hasPercentage":false,"hasLineThrough":false},{"price":50,"code":"USD","discount":0,"hasPercentage":false,"hasLineThrough":true},{"price":35.5,"code":"USD","discount":0,"hasPercentage":false,"hasLineThrough":false},{"price":170,"code":"USD","discount":0,"hasPercentage":false,"hasLineThrough":true},{"price":93.99,"code":"USD","discount":0,"hasPercentage":false,"hasLineThrough":false},{"price":120,"code":"USD","discount":0,"hasPercentage":false,"hasLineThrough":true},{"price":96,"code":"USD","discount":0,"hasPercentage":false,"hasLineThrough":false},{"price":40,"code":"USD","discount":0,"hasPercentage":false,"hasLineThrough":true},{"price":27.6,"code":"USD","discount":0,"hasPercentage":false,"hasLineThrough":false},{"price":60,"code":"USD","discount":0,"hasPercentage":false,"hasLineThrough":true},{"price":45.6,"code":"USD","discount":0,"hasPercentage":false,"hasLineThrough":false},{"price":55,"code":"USD","discount":0,"hasPercentage":false,"hasLineThrough":true},{"price":39.05,"code":"USD","discount":0,"hasPercentage":false,"hasLineThrough":false},{"price":55,"code":"USD","discount":0,"hasPercentage":false,"hasLineThrough":true},{"price":39.05,"code":"USD","discount":0,"hasPercentage":false,"hasLineThrough":false},{"price":55,"code":"USD","discount":0,"hasPercentage":false,"hasLineThrough":true},{"price":42.9,"code":"USD","discount":0,"hasPercentage":false,"hasLineThrough":false},{"price":55,"code":"USD","discount":0,"hasPercentage":false,"hasLineThrough":true},{"price":43.45,"code":"USD","discount":0,"hasPercentage":false,"hasLineThrough":false},{"price":60,"code":"USD","discount":0,"hasPercentage":false,"hasLineThrough":true},{"price":45,"code":"USD","discount":0,"hasPercentage":false,"hasLineThrough":false},{"price":30,"code":"USD","discount":0,"hasPercentage":false,"hasLineThrough":true},{"price":18.6,"code":"USD","discount":0,"hasPercentage":false,"hasLineThrough":false}]}