{"url":"http://neuemesser.com/","isFake":true,"links":[],"prices":[{"price":92.99,"code":"EUR","discount":0.45,"hasPercentage":false,"hasLineThrough":true},{"price":93.99,"code":"EUR","discount":0.79,"hasPercentage":false,"hasLineThrough":true},{"price":91.99,"code":"EUR","discount":0.54,"hasPercentage":false,"hasLineThrough":true},{"price":45.99,"code":"EUR","discount":0.29,"hasPercentage":false,"hasLineThrough":true},{"price":90.99,"code":"EUR","discount":0.29,"hasPercentage":false,"hasLineThrough":true},{"price":42.99,"code":"EUR","discount":0.28,"hasPercentage":false,"hasLineThrough":true},{"price":91.99,"code":"EUR","discount":0.49,"hasPercentage":false,"hasLineThrough":true},{"price":89.99,"code":"EUR","discount":0.52,"hasPercentage":false,"hasLineThrough":true},{"price":95.99,"code":"EUR","discount":0.63,"hasPercentage":false,"hasLineThrough":true},{"price":91.99,"code":"EUR","discount":0.64,"hasPercentage":false,"hasLineThrough":true},{"price":95.99,"code":"EUR","discount":0.6,"hasPercentage":false,"hasLineThrough":true},{"price":89.99,"code":"EUR","discount":0.72,"hasPercentage":false,"hasLineThrough":true},{"price":93.99,"code":"EUR","discount":0.66,"hasPercentage":false,"hasLineThrough":true},{"price":90.99,"code":"EUR","discount":0.66,"hasPercentage":false,"hasLineThrough":true},{"price":96.99,"code":"EUR","discount":0.6,"hasPercentage":false,"hasLineThrough":true},{"price":91.99,"code":"EUR","discount":0.74,"hasPercentage":false,"hasLineThrough":true},{"price":22.99,"code":"EUR","discount":0.28,"hasPercentage":false,"hasLineThrough":true},{"price":95.99,"code":"EUR","discount":0.63,"hasPercentage":false,"hasLineThrough":true},{"price":89.99,"code":"EUR","discount":0.51,"hasPercentage":false,"hasLineThrough":true},{"price":98.99,"code":"EUR","discount":0.63,"hasPercentage":false,"hasLineThrough":true},{"price":96.99,"code":"EUR","discount":0.56,"hasPercentage":false,"hasLineThrough":true},{"price":94.99,"code":"EUR","discount":0.36,"hasPercentage":false,"hasLineThrough":true},{"price":97.99,"code":"EUR","discount":0.3,"hasPercentage":false,"hasLineThrough":true},{"price":95.99,"code":"EUR","discount":0.36,"hasPercentage":false,"hasLineThrough":true},{"price":93.99,"code":"EUR","discount":0.44,"hasPercentage":false,"hasLineThrough":true},{"price":9.99,"code":"EUR","discount":0.29,"hasPercentage":false,"hasLineThrough":true},{"price":41.99,"code":"EUR","discount":0.29,"hasPercentage":false,"hasLineThrough":true},{"price":49.99,"code":"EUR","discount":0.29,"hasPercentage":false,"hasLineThrough":true},{"price":99.99,"code":"EUR","discount":0.61,"hasPercentage":false,"hasLineThrough":true},{"price":89.99,"code":"EUR","discount":0.5,"hasPercentage":false,"hasLineThrough":true},{"price":98.99,"code":"EUR","discount":0.29,"hasPercentage":false,"hasLineThrough":true},{"price":33.99,"code":"EUR","discount":0.29,"hasPercentage":false,"hasLineThrough":true},{"price":13.99,"code":"EUR","discount":0.26,"hasPercentage":false,"hasLineThrough":true},{"price":90.99,"code":"EUR","discount":0.29,"hasPercentage":false,"hasLineThrough":true},{"price":56.99,"code":"EUR","discount":0.29,"hasPercentage":false,"hasLineThrough":true},{"price":96.99,"code":"EUR","discount":0.53,"hasPercentage":false,"hasLineThrough":true},{"price":259,"code":"EUR","discount":0,"hasPercentage":false,"hasLineThrough":true},{"price":95.99,"code":"EUR","discount":0,"hasPercentage":false,"hasLineThrough":false},{"price":259,"code":"EUR","discount":0,"hasPercentage":false,"hasLineThrough":true},{"price":91.99,"code":"EUR","discount":0,"hasPercentage":false,"hasLineThrough":false},{"price":239,"code":"EUR","discount":0,"hasPercentage":false,"hasLineThrough":true},{"price":95.99,"code":"EUR","discount":0,"hasPercentage":false,"hasLineThrough":false},{"price":320,"code":"EUR","discount":0,"hasPercentage":false,"hasLineThrough":true},{"price":89.99,"code":"EUR","discount":0,"hasPercentage":false,"hasLineThrough":false},{"price":170,"code":"EUR","discount":0,"hasPercentage":false,"hasLineThrough":true},{"price":92.99,"code":"EUR","discount":0,"hasPercentage":false,"hasLineThrough":false},{"price":449,"code":"EUR","discount":0,"hasPercentage":false,"hasLineThrough":true},{"price":93.99,"code":"EUR","discount":0,"hasPercentage":false,"hasLineThrough":false},{"price":199,"code":"EUR","discount":0,"hasPercentage":false,"hasLineThrough":true},{"price":91.99,"code":"EUR","discount":0,"hasPercentage":false,"hasLineThrough":false},{"price":65,"code":"EUR","discount":0,"hasPercentage":false,"hasLineThrough":true},{"price":45.99,"code":"EUR","discount":0,"hasPercentage":false,"hasLineThrough":false},{"price":159,"code":"EUR","discount":0,"hasPercentage":false,"hasLineThrough":true},{"price":99.99,"code":"EUR","discount":0,"hasPercentage":false,"hasLineThrough":false},{"price":179,"code":"EUR","discount":0,"hasPercentage":false,"hasLineThrough":true},{"price":99.99,"code":"EUR","discount":0,"hasPercentage":false,"hasLineThrough":false},{"price":399,"code":"EUR","discount":0,"hasPercentage":false,"hasLineThrough":true},{"price":99.99,"code":"EUR","discount":0,"hasPercentage":false,"hasLineThrough":false},{"price":179,"code":"EUR","discount":0,"hasPercentage":false,"hasLineThrough":true},{"price":99.99,"code":"EUR","discount":0,"hasPercentage":false,"hasLineThrough":false}]}