{"url":"http://olangsdeutschland.de/","isFake":true,"links":["https://www.olangsdeutschland.de/","https://www.olangsdeutschland.de/shopping_cart.html","https://www.olangsdeutschland.de/collections/stiefel-c-1.html?&gender=1","https://www.olangsdeutschland.de/collections/stiefel-halbhohe-stiefel-c-1_4.html?&gender=1","https://www.olangsdeutschland.de/collections/stiefel-schneestiefel-c-1_2.html?&gender=1","https://www.olangsdeutschland.de/collections/stiefel-stiefeletten-c-1_3.html?&gender=1","https://www.olangsdeutschland.de/collections/stiefel-winterstiefel-c-1_5.html?&gender=1","https://www.olangsdeutschland.de/collections/stiefel-c-1.html?&gender=2","https://www.olangsdeutschland.de/collections/stiefel-schneestiefel-c-1_2.html?&gender=2","https://www.olangsdeutschland.de/collections/stiefel-stiefeletten-c-1_3.html?&gender=2","https://www.olangsdeutschland.de/collections/stiefel-winterstiefel-c-1_5.html?&gender=2","https://www.olangsdeutschland.de/collections/stiefel-c-1.html?&gender=3","https://www.olangsdeutschland.de/collections/stiefel-schneestiefel-c-1_2.html?&gender=3","https://www.olangsdeutschland.de/collections/stiefel-c-1.html?gender=1","https://www.olangsdeutschland.de/collections/stiefel-c-1.html?gender=2","https://www.olangsdeutschland.de/collections/stiefel-c-1.html?gender=3","https://www.olangsdeutschland.de/collections/stiefel-c-1.html","https://www.olangsdeutschland.de/about_us.html","https://www.olangsdeutschland.de/shippinginfo.html","https://www.olangsdeutschland.de/privacy.html","https://www.olangsdeutschland.de/contact_us.html","https://www.olangsdeutschland.de/return.html","https://www.olangsdeutschland.de/payment_method.html","https://www.olangsdeutschland.de/outlet.html","https://www.facebook.com/sharer/sharer.php?u=http://www.olangsdeutschland.de/","https://twitter.com/intent/tweet/?url=http://www.olangsdeutschland.de/","https://www.pinterest.com/pin/create/button/?url=http://www.olangsdeutschland.de/","http://www.tumblr.com/share/link?url=http://www.olangsdeutschland.de/","https://plus.google.com/share?url=http://www.olangsdeutschland.de/"],"prices":[{"price":87.69,"code":"EUR","discount":0.41,"hasPercentage":false,"hasLineThrough":true},{"price":87.49,"code":"EUR","discount":0.37,"hasPercentage":false,"hasLineThrough":true},{"price":92.87,"code":"EUR","discount":0.42,"hasPercentage":false,"hasLineThrough":true},{"price":92.71,"code":"EUR","discount":0.39,"hasPercentage":false,"hasLineThrough":true},{"price":87.57,"code":"EUR","discount":0.39,"hasPercentage":false,"hasLineThrough":true},{"price":87.54,"code":"EUR","discount":0.38,"hasPercentage":false,"hasLineThrough":true},{"price":92.72,"code":"EUR","discount":0.39,"hasPercentage":false,"hasLineThrough":true},{"price":87.49,"code":"EUR","discount":0.37,"hasPercentage":false,"hasLineThrough":true},{"price":77.26,"code":"EUR","discount":0.39,"hasPercentage":false,"hasLineThrough":true},{"price":92.71,"code":"EUR","discount":0.39,"hasPercentage":false,"hasLineThrough":true},{"price":87.39,"code":"EUR","discount":0.35,"hasPercentage":false,"hasLineThrough":true},{"price":92.79,"code":"EUR","discount":0.4,"hasPercentage":false,"hasLineThrough":true}]}