{"url":"http://panamajack-wien.at/","isFake":true,"links":["https://www.panamajack-wien.at/","https://www.panamajack-wien.at/damen-c-1.html","https://www.panamajack-wien.at/herren-c-12.html","https://www.panamajack-wien.at/login.html","https://www.panamajack-wien.at/shopping_cart.html","https://www.panamajack-wien.at/damen-biker-boots-c-1_11.html","https://www.panamajack-wien.at/damen-chelsea-boots-c-1_9.html","https://www.panamajack-wien.at/damen-chukka-boots-c-1_8.html","https://www.panamajack-wien.at/damen-clogs-c-1_7.html","https://www.panamajack-wien.at/damen-goretex%C2%AE-c-1_6.html","https://www.panamajack-wien.at/damen-hohe-stiefel-c-1_5.html","https://www.panamajack-wien.at/damen-schn%C3%BCrstiefel-c-1_3.html","https://www.panamajack-wien.at/damen-stiefel-c-1_10.html","https://www.panamajack-wien.at/damen-wanderschuhe-c-1_4.html","https://www.panamajack-wien.at/damen-winterstiefel-c-1_2.html","https://www.panamajack-wien.at/herren-ankle-boots-c-12_20.html","https://www.panamajack-wien.at/herren-chelsea-boots-c-12_18.html","https://www.panamajack-wien.at/herren-chukka-boots-c-12_17.html","https://www.panamajack-wien.at/herren-goretex%C2%AE-c-12_16.html","https://www.panamajack-wien.at/herren-schn%C3%BCrstiefel-c-12_15.html","https://www.panamajack-wien.at/herren-schuhe-c-12_14.html","https://www.panamajack-wien.at/herren-stiefel-c-12_19.html","https://www.panamajack-wien.at/herren-winterstiefel-c-12_13.html","https://www.facebook.com/sharer/sharer.php?u=http://www.panamajack-wien.at/","https://twitter.com/intent/tweet/?url=http://www.panamajack-wien.at/","https://www.pinterest.com/pin/create/button/?url=http://www.panamajack-wien.at/","http://www.tumblr.com/share/link?url=http://www.panamajack-wien.at/","https://plus.google.com/share?url=http://www.panamajack-wien.at/","https://www.panamajack-wien.at/shippinginfo.html","https://www.panamajack-wien.at/privacy.html","https://www.panamajack-wien.at/contact_us.html","https://www.panamajack-wien.at/site_map.html","https://www.panamajack-wien.at/outlet.html"],"prices":[{"price":76,"code":"EUR","discount":0.46,"hasPercentage":false,"hasLineThrough":true},{"price":76,"code":"EUR","discount":0.46,"hasPercentage":false,"hasLineThrough":true},{"price":86,"code":"EUR","discount":0.46,"hasPercentage":false,"hasLineThrough":true},{"price":100,"code":"EUR","discount":0.46,"hasPercentage":false,"hasLineThrough":true},{"price":81,"code":"EUR","discount":0.46,"hasPercentage":false,"hasLineThrough":true},{"price":81,"code":"EUR","discount":0.46,"hasPercentage":false,"hasLineThrough":true},{"price":86,"code":"EUR","discount":0.46,"hasPercentage":false,"hasLineThrough":true},{"price":86,"code":"EUR","discount":0.46,"hasPercentage":false,"hasLineThrough":true},{"price":86,"code":"EUR","discount":0.46,"hasPercentage":false,"hasLineThrough":true},{"price":76,"code":"EUR","discount":0.46,"hasPercentage":false,"hasLineThrough":true},{"price":76,"code":"EUR","discount":0.46,"hasPercentage":false,"hasLineThrough":true},{"price":76,"code":"EUR","discount":0.46,"hasPercentage":false,"hasLineThrough":true},{"price":86,"code":"EUR","discount":0.46,"hasPercentage":false,"hasLineThrough":true},{"price":100,"code":"EUR","discount":0.46,"hasPercentage":false,"hasLineThrough":true},{"price":81,"code":"EUR","discount":0.46,"hasPercentage":false,"hasLineThrough":true},{"price":81,"code":"EUR","discount":0.46,"hasPercentage":false,"hasLineThrough":true},{"price":86,"code":"EUR","discount":0.46,"hasPercentage":false,"hasLineThrough":true},{"price":86,"code":"EUR","discount":0.46,"hasPercentage":false,"hasLineThrough":true},{"price":86,"code":"EUR","discount":0.46,"hasPercentage":false,"hasLineThrough":true},{"price":76,"code":"EUR","discount":0.46,"hasPercentage":false,"hasLineThrough":true},{"price":76,"code":"EUR","discount":0.46,"hasPercentage":false,"hasLineThrough":true},{"price":76,"code":"EUR","discount":0.46,"hasPercentage":false,"hasLineThrough":true},{"price":86,"code":"EUR","discount":0.46,"hasPercentage":false,"hasLineThrough":true},{"price":100,"code":"EUR","discount":0.46,"hasPercentage":false,"hasLineThrough":true}]}