{"url":"http://prostovit-official.site/","isFake":true,"links":["https://prostovit-official.site/","https://deutschland.prostovit-official.site/","https://spain.prostovit-official.site/","https://spain-eu.prostovit-official.site/","https://spain-gl.prostovit-official.site/","https://italy.prostovit-official.site/","https://portugal.prostovit-official.site/","https://portugal-gl.prostovit-official.site/","https://bulgaria.prostovit-official.site/","https://belgium.prostovit-official.site/","https://austria.prostovit-official.site/","https://hungary.prostovit-official.site/","https://greece.prostovit-official.site/","https://cyprus.prostovit-official.site/","https://cyprus-tr.prostovit-official.site/","https://luxembourg.prostovit-official.site/","https://luxembourg-fr.prostovit-official.site/","https://netherlands.prostovit-official.site/","https://poland.prostovit-official.site/","https://romania.prostovit-official.site/","https://slovakia.prostovit-official.site/","https://slovenia.prostovit-official.site/","https://croatia.prostovit-official.site/","https://czech.prostovit-official.site/","https://switzerland.prostovit-official.site/","https://switzerland-fr.prostovit-official.site/","https://switzerland-it.prostovit-official.site/","https://latvia.prostovit-official.site/","https://lithuania.prostovit-official.site/","https://estonia.prostovit-official.site/","https://www.facebook.com/sharer.php?src=sp&u=prostovit-official.site","http://twitter.com/share?text=Prostovit%20site%20officiel:%20acheter,%20prix,%20composition%20gouttes,%20commentaires.&url=prostovit-official.site","https://deutschland.prostovit-official.site/images/0of6gxdrvarop.png","https://spain.prostovit-official.site/images/rni8xewqrc2.png","https://italy.prostovit-official.site/images/ke96fa2jila9qx.png","https://portugal.prostovit-official.site/images/wsdcfnt6h9orwrmmr.png","https://bulgaria.prostovit-official.site/images/stg60m9wd28y8hc.png","https://belgium.prostovit-official.site/images/4aokrjqelz.png","https://austria.prostovit-official.site/images/ckhz09dz09.png","https://hungary.prostovit-official.site/images/1crt8g0jq98ty24le1t.png","https://greece.prostovit-official.site/images/2pgqb4phy6t.png","https://cyprus.prostovit-official.site/images/sp3s101gnwvw.png","https://luxembourg.prostovit-official.site/images/p508g9o63ers0wiuec.png","https://netherlands.prostovit-official.site/images/isxmka3o8ooc0zym.png","https://poland.prostovit-official.site/images/gxtm5oudlly4fqcc.png","https://romania.prostovit-official.site/images/dq2r2f7chrdc.png","https://slovakia.prostovit-official.site/images/ejkmlf32ujc8bt.png","https://slovenia.prostovit-official.site/images/czjii1jokehodn.png","https://croatia.prostovit-official.site/images/j9mculf84k4ty3b.png","https://czech.prostovit-official.site/images/p2flc9funvsvdc55u2o.png","https://switzerland.prostovit-official.site/images/hpoljnkc8xr9pia.png","https://latvia.prostovit-official.site/images/lcu2tjm9d55h3hq.png","https://lithuania.prostovit-official.site/images/dhyfiy3w90i7.png","https://estonia.prostovit-official.site/images/pccdtde2sr8kd8ltymof.png","http://schema.org/InStock","https://prostovit-official.site/des-articles/8_comment%20traiter%20la%20prostatite","https://prostovit-official.site/des-articles/7_m%C3%A9dicament%20pour%20la%20prostatite","https://prostovit-official.site/des-articles/6_prostatite%20chronique"],"prices":[{"price":39,"code":"EUR","discount":0.5,"hasPercentage":false,"hasLineThrough":true},{"price":39,"code":"EUR","discount":0.5,"hasPercentage":false,"hasLineThrough":true}]}