{"url":"http://stylereduction.com/","isFake":true,"links":[],"prices":[{"price":0,"code":"USD","discount":0,"hasPercentage":false,"hasLineThrough":false},{"price":65.95,"code":"USD","discount":0.3,"hasPercentage":false,"hasLineThrough":true},{"price":23.95,"code":"USD","discount":0.27,"hasPercentage":false,"hasLineThrough":true},{"price":30.95,"code":"USD","discount":0.3,"hasPercentage":false,"hasLineThrough":true},{"price":90.95,"code":"USD","discount":0.51,"hasPercentage":false,"hasLineThrough":true},{"price":34.95,"code":"USD","discount":0.29,"hasPercentage":false,"hasLineThrough":true},{"price":32.95,"code":"USD","discount":0.3,"hasPercentage":false,"hasLineThrough":true},{"price":31.95,"code":"USD","discount":0.29,"hasPercentage":false,"hasLineThrough":true},{"price":6.95,"code":"USD","discount":0.23,"hasPercentage":false,"hasLineThrough":true},{"price":94.95,"code":"USD","discount":0.6,"hasPercentage":false,"hasLineThrough":true},{"price":98.95,"code":"USD","discount":0.79,"hasPercentage":false,"hasLineThrough":true},{"price":92.95,"code":"USD","discount":0.66,"hasPercentage":false,"hasLineThrough":true},{"price":97.95,"code":"USD","discount":0.55,"hasPercentage":false,"hasLineThrough":true},{"price":97.95,"code":"USD","discount":0.77,"hasPercentage":false,"hasLineThrough":true},{"price":90.95,"code":"USD","discount":0.7,"hasPercentage":false,"hasLineThrough":true},{"price":89.95,"code":"USD","discount":0.8,"hasPercentage":false,"hasLineThrough":true},{"price":91.95,"code":"USD","discount":0.78,"hasPercentage":false,"hasLineThrough":true},{"price":30.99,"code":"USD","discount":0,"hasPercentage":false,"hasLineThrough":true},{"price":21.95,"code":"USD","discount":0,"hasPercentage":false,"hasLineThrough":false}]}